MANIFEST.in
README.md
requirements.txt
setup.py
vialink/utils/logs/__init__.py
vialink/utils/logs/logs.py
vialink/utils/logs/settings.py
vialink_utils_logs.egg-info/PKG-INFO
vialink_utils_logs.egg-info/SOURCES.txt
vialink_utils_logs.egg-info/dependency_links.txt
vialink_utils_logs.egg-info/requires.txt
vialink_utils_logs.egg-info/top_level.txt