Metadata-Version: 2.1
Name: vialink-utils-logs
Version: 1.0.0
Summary: Vialink Utils
Home-page: 
Author: yurananatul.m
Author-email: yurananatul.m@via.link
License: Apache 2.0
Requires-Python: >=3.7
